{
  "iteration": 24,
  "question_id": "index_23",
  "results_by_threshold": {
    "0.65": {
      "detected_pairs": [
        {
          "chain1_id": "q24_c1",
          "chain2_id": "q24_c2",
          "thought1_idx": 7,
          "thought2_idx": 2,
          "text1": "Wait, but if the list is arranged as [x, y,9,9], then the median is (y +9)/2.\n\nThis median must be an integer not present in the list.\n\nSo (y +9)/2 must be integer, so y +9 must be even, so y must be odd or even depending on 9. 9 is odd, so y must be odd since odd + odd = even.",
          "text2": "Wait, no. If the list has an even number of elements, the median is the average of the two middle numbers. So, if it's a positive integer, that average must be an integer, so the two middle numbers must add up to an even number. But if the median isn't in the list, that means that the two middle numbers are different, perhaps? Because if they were the same, their average would be that number, which would be in the list, right?\n\nBut in this problem, the median is a positive integer not in the list. So, if n is even, the two middle numbers must average to some integer 'm' that's not in the list. So, for example, two middle numbers could be 8 and 10, giving a median of 9, which isn't in the list.",
          "score": 0.8306614756584167
        }
      ],
      "num_detected": 1,
      "num_same_answer": 1,
      "same_answer_perc": 100.0
    },
    "0.7": {
      "detected_pairs": [
        {
          "chain1_id": "q24_c1",
          "chain2_id": "q24_c2",
          "thought1_idx": 7,
          "thought2_idx": 2,
          "text1": "Wait, but if the list is arranged as [x, y,9,9], then the median is (y +9)/2.\n\nThis median must be an integer not present in the list.\n\nSo (y +9)/2 must be integer, so y +9 must be even, so y must be odd or even depending on 9. 9 is odd, so y must be odd since odd + odd = even.",
          "text2": "Wait, no. If the list has an even number of elements, the median is the average of the two middle numbers. So, if it's a positive integer, that average must be an integer, so the two middle numbers must add up to an even number. But if the median isn't in the list, that means that the two middle numbers are different, perhaps? Because if they were the same, their average would be that number, which would be in the list, right?\n\nBut in this problem, the median is a positive integer not in the list. So, if n is even, the two middle numbers must average to some integer 'm' that's not in the list. So, for example, two middle numbers could be 8 and 10, giving a median of 9, which isn't in the list.",
          "score": 0.8306614756584167
        }
      ],
      "num_detected": 1,
      "num_same_answer": 1,
      "same_answer_perc": 100.0
    },
    "0.75": {
      "detected_pairs": [
        {
          "chain1_id": "q24_c1",
          "chain2_id": "q24_c2",
          "thought1_idx": 7,
          "thought2_idx": 2,
          "text1": "Wait, but if the list is arranged as [x, y,9,9], then the median is (y +9)/2.\n\nThis median must be an integer not present in the list.\n\nSo (y +9)/2 must be integer, so y +9 must be even, so y must be odd or even depending on 9. 9 is odd, so y must be odd since odd + odd = even.",
          "text2": "Wait, no. If the list has an even number of elements, the median is the average of the two middle numbers. So, if it's a positive integer, that average must be an integer, so the two middle numbers must add up to an even number. But if the median isn't in the list, that means that the two middle numbers are different, perhaps? Because if they were the same, their average would be that number, which would be in the list, right?\n\nBut in this problem, the median is a positive integer not in the list. So, if n is even, the two middle numbers must average to some integer 'm' that's not in the list. So, for example, two middle numbers could be 8 and 10, giving a median of 9, which isn't in the list.",
          "score": 0.8306614756584167
        }
      ],
      "num_detected": 1,
      "num_same_answer": 1,
      "same_answer_perc": 100.0
    },
    "0.8": {
      "detected_pairs": [
        {
          "chain1_id": "q24_c1",
          "chain2_id": "q24_c2",
          "thought1_idx": 7,
          "thought2_idx": 2,
          "text1": "Wait, but if the list is arranged as [x, y,9,9], then the median is (y +9)/2.\n\nThis median must be an integer not present in the list.\n\nSo (y +9)/2 must be integer, so y +9 must be even, so y must be odd or even depending on 9. 9 is odd, so y must be odd since odd + odd = even.",
          "text2": "Wait, no. If the list has an even number of elements, the median is the average of the two middle numbers. So, if it's a positive integer, that average must be an integer, so the two middle numbers must add up to an even number. But if the median isn't in the list, that means that the two middle numbers are different, perhaps? Because if they were the same, their average would be that number, which would be in the list, right?\n\nBut in this problem, the median is a positive integer not in the list. So, if n is even, the two middle numbers must average to some integer 'm' that's not in the list. So, for example, two middle numbers could be 8 and 10, giving a median of 9, which isn't in the list.",
          "score": 0.8306614756584167
        }
      ],
      "num_detected": 1,
      "num_same_answer": 1,
      "same_answer_perc": 100.0
    },
    "0.85": {
      "detected_pairs": [
        {
          "chain1_id": "q24_c2",
          "chain2_id": "q24_c1",
          "thought1_idx": 9,
          "thought2_idx": 2,
          "text1": "Wait, no, that's not possible. Because if n is odd, the median is the (n+1)/2-th element, which is in the list. So, if the median isn't in the list, then n must be even, because for even n, the median is the average of two middle numbers, which may not be present in the list.\n\nSo, that suggests that n is even. Let's proceed with that.\n\nSo, let's assume that the list has even number of elements. Let's denote n = 2m, where m is an integer. So, the two middle numbers are the m-th and (m+1)-th elements when sorted.\n\nTheir average is the median, which is a positive integer not in the list. So, let's say the median is 'm_val', which is not in the list.\n\nSo, for example, suppose the two middle numbers are a and b, such that (a + b)/2 = m_val, and m_val is not in the list.\n\nSince 9 is the mode, it's in the list multiple times. Let's see.\n\nNow, moving on to the sum.\n\nThe sum of the list is 30. So, the total of all the elements is 30.\n\nWe have to find a list that satisfies all these conditions.\n\nLet me try to outline a possible approach.\n\nFirst, decide on the length of the list. Let's assume n is even, so n = 2m. The median is the average of the m-th and (m+1)-th elements.\n\nSince 9 is the mode, it must appear more times than any other number. So, the count of 9s must be higher than the count of any other number.\n\nLet me try to construct such a list.\n\nLet me think of a possible minimal case. Let's try small n first.",
          "text2": "Wait, the problem doesn't specify the length of the list, right? So I might have to figure that out as part of the solution.\n\nLet me consider the possible number of elements.\n\nLet's start with small n.\n\nCase 1: n is 2.\n\nBut for n=2, the median would be the average of the two numbers. Since the median is not in the list, the average must be an integer not present. But since the list has two numbers, their average must be an integer. However, for the sum to be 30, each number would be 15. But then both numbers are 15, so the mode would be 15, but the problem says the mode is 9. So n=2 is impossible.\n\nCase 2: n=3.\n\nIn this case, the median is the second number when arranged in order. Since the median is an integer not in the list, the second number must be something else. Let's see.\n\nThe sum is 30, so the three numbers add up to 30. The mode is 9, so 9 must appear at least twice because in a list of 3, the mode has to appear more than once. So the list would have two 9s and one other number. Let's denote the numbers as a, 9, 9, where a \u22649 \u22649.",
          "score": 0.9050429463386536
        }
      ],
      "num_detected": 1,
      "num_same_answer": 1,
      "same_answer_perc": 100.0
    },
    "0.9": {
      "detected_pairs": [
        {
          "chain1_id": "q24_c2",
          "chain2_id": "q24_c1",
          "thought1_idx": 9,
          "thought2_idx": 2,
          "text1": "Wait, no, that's not possible. Because if n is odd, the median is the (n+1)/2-th element, which is in the list. So, if the median isn't in the list, then n must be even, because for even n, the median is the average of two middle numbers, which may not be present in the list.\n\nSo, that suggests that n is even. Let's proceed with that.\n\nSo, let's assume that the list has even number of elements. Let's denote n = 2m, where m is an integer. So, the two middle numbers are the m-th and (m+1)-th elements when sorted.\n\nTheir average is the median, which is a positive integer not in the list. So, let's say the median is 'm_val', which is not in the list.\n\nSo, for example, suppose the two middle numbers are a and b, such that (a + b)/2 = m_val, and m_val is not in the list.\n\nSince 9 is the mode, it's in the list multiple times. Let's see.\n\nNow, moving on to the sum.\n\nThe sum of the list is 30. So, the total of all the elements is 30.\n\nWe have to find a list that satisfies all these conditions.\n\nLet me try to outline a possible approach.\n\nFirst, decide on the length of the list. Let's assume n is even, so n = 2m. The median is the average of the m-th and (m+1)-th elements.\n\nSince 9 is the mode, it must appear more times than any other number. So, the count of 9s must be higher than the count of any other number.\n\nLet me try to construct such a list.\n\nLet me think of a possible minimal case. Let's try small n first.",
          "text2": "Wait, the problem doesn't specify the length of the list, right? So I might have to figure that out as part of the solution.\n\nLet me consider the possible number of elements.\n\nLet's start with small n.\n\nCase 1: n is 2.\n\nBut for n=2, the median would be the average of the two numbers. Since the median is not in the list, the average must be an integer not present. But since the list has two numbers, their average must be an integer. However, for the sum to be 30, each number would be 15. But then both numbers are 15, so the mode would be 15, but the problem says the mode is 9. So n=2 is impossible.\n\nCase 2: n=3.\n\nIn this case, the median is the second number when arranged in order. Since the median is an integer not in the list, the second number must be something else. Let's see.\n\nThe sum is 30, so the three numbers add up to 30. The mode is 9, so 9 must appear at least twice because in a list of 3, the mode has to appear more than once. So the list would have two 9s and one other number. Let's denote the numbers as a, 9, 9, where a \u22649 \u22649.",
          "score": 0.9050429463386536
        }
      ],
      "num_detected": 1,
      "num_same_answer": 1,
      "same_answer_perc": 100.0
    },
    "0.95": {
      "detected_pairs": [],
      "num_detected": 0,
      "num_same_answer": 0,
      "same_answer_perc": null
    }
  }
}